laporte/__init__.py
laporte/__main__.py
laporte/argparser.py
laporte/server.py
laporte/version.py
laporte/api/__init__.py
laporte/app/__init__.py
laporte/app/event_id.py
laporte/app/request_id.py
laporte/client/__init__.py
laporte/client/metrics.py
laporte/client/sio.py
laporte/core/__init__.py
laporte/core/sensor.py
laporte/core/sensors.py
laporte/logger/__init__.py
laporte/logger/handlers.py
laporte/metrics/__init__.py
laporte/metrics/collector.py
laporte/metrics/common.py
laporte/web/__init__.py
laporte/web/static/favicon.svg
laporte/web/static/css/log.css
laporte/web/static/js/data.js
laporte/web/static/js/events.js
laporte/web/static/js/log.js
laporte/web/static/js/metrics.js
laporte/web/static/js/scheduler.js
laporte/web/static/js/shared.js
laporte/web/templates/base.html
laporte/web/templates/data.html
laporte/web/templates/doc.html
laporte/web/templates/events.html
laporte/web/templates/info.html
laporte/web/templates/log.html
laporte/web/templates/metrics.html
laporte/web/templates/scheduler.html
laporte-0.7.5.dist-info/LICENSE
laporte-0.7.5.dist-info/METADATA
laporte-0.7.5.dist-info/WHEEL
laporte-0.7.5.dist-info/entry_points.txt
laporte-0.7.5.dist-info/top_level.txt
laporte-0.7.5.dist-info/RECORD
