Metadata-Version: 2.1
Name: laporte
Version: 0.7.5
Summary: Push gateway for processing metrics with automation and states.
Home-page: https://github.com/vinklat/laporte
Author: Václav Vinklát
Author-email: vin@email.cz
License: UNKNOWN
Platform: UNKNOWN
Classifier: Programming Language :: Python :: 3
Classifier: License :: OSI Approved :: MIT License
Classifier: Operating System :: OS Independent
Requires-Dist: flask
Requires-Dist: flask-restx
Requires-Dist: flask-socketio
Requires-Dist: python-socketio[client]
Requires-Dist: bootstrap-flask
Requires-Dist: prometheus-client
Requires-Dist: apscheduler
Requires-Dist: gevent
Requires-Dist: gevent-websocket
Requires-Dist: pyyaml
Requires-Dist: jinja2
Requires-Dist: asteval
Requires-Dist: numpy
